arguments/argument.py
consoles/abstract_console.py
console_creator-0.0.0a1.dist-info/LICENSE
console_creator-0.0.0a1.dist-info/METADATA
console_creator-0.0.0a1.dist-info/WHEEL
console_creator-0.0.0a1.dist-info/top_level.txt
console_creator-0.0.0a1.dist-info/RECORD
