Metadata-Version: 2.1
Name: console-creator
Version: 0.0.0a1
Summary: With console_creator, create consoles (python like, cdm like or java like) for your softwere.
Author-email: Cyprien BONTRON <c.b.e.python@gmail.com>
Maintainer-email: Cyprien BONTRON <c.b.e.python@gmail.com>
License: Creative Commons Attribution-NonCommercial-ShareAlike 4.0 International Public License        
Project-URL: Download-URL, https://pypi.org/project/console_creator/
Classifier: Programming Language :: Python :: 3.7
Classifier: Programming Language :: Python :: 3.8
Classifier: Programming Language :: Python :: 3.9
Classifier: Programming Language :: Python :: 3.10
Classifier: Natural Language :: English
Classifier: Intended Audience :: Developers
Classifier: Intended Audience :: System Administrators
Classifier: Topic :: Scientific/Engineering :: Human Machine Interfaces
Classifier: Topic :: System :: Systems Administration
Classifier: Topic :: System :: Shells
Classifier: Topic :: Utilities
Classifier: License :: Free for non-commercial use
Classifier: Development Status :: 1 - Planning
Requires-Python: >=3.7
License-File: LICENSE
